{
   "special_schools" : {
      "特別支援学校ねむの木" : {
         "location_area" : "掛川市"
      },
      "静岡大学教育学部附属特別支援学校" : {
         "sort_name" : "しすおかたいかくきよういくかくふふそくとくへつしえんかつこう"
      },
      "静岡県立中央特別支援学校" : {
         "location_area" : "静岡市",
         "short_name" : "中央特別支援学校"
      },
      "静岡県立天竜特別支援学校" : {
         "location_area" : "浜松市",
         "short_name" : "天竜特別支援学校"
      },
      "静岡県立富士特別支援学校" : {
         "location_area" : "富士市",
         "short_name" : "富士特別支援学校"
      },
      "静岡県立御殿場特別支援学校" : {
         "location_area" : "御殿場市",
         "short_name" : "御殿場特別支援学校"
      },
      "静岡県立東部特別支援学校" : {
         "location_area" : "伊豆の国市",
         "short_name" : "東部特別支援学校"
      },
      "静岡県立東部特別支援学校伊東分校" : {
         "location_area" : "伊豆の国市",
         "short_name" : "東部特別支援学校伊東分校"
      },
      "静岡県立東部特別支援学校伊豆つくし分教室" : {
         "location_area" : "伊豆の国市",
         "short_name" : "東部特別支援学校伊豆つくし分教室"
      },
      "静岡県立東部特別支援学校伊豆高原分校" : {
         "location_area" : "伊豆の国市",
         "short_name" : "東部特別支援学校伊豆高原分校"
      },
      "静岡県立東部特別支援学校川奈分校" : {
         "location_area" : "伊豆の国市",
         "short_name" : "東部特別支援学校川奈分校"
      },
      "静岡県立沼津特別支援学校" : {
         "location_area" : "沼津市",
         "short_name" : "沼津特別支援学校"
      },
      "静岡県立沼津聴覚特別支援学校" : {
         "location_area" : "沼津市",
         "short_name" : "沼津聴覚特別支援学校"
      },
      "静岡県立沼津視覚特別支援学校" : {
         "location_area" : "沼津市",
         "short_name" : "沼津視覚特別支援学校"
      },
      "静岡県立浜北特別支援学校" : {
         "location_area" : "浜松市",
         "short_name" : "浜北特別支援学校"
      },
      "静岡県立浜名特別支援学校" : {
         "location_area" : "湖西市",
         "short_name" : "浜名特別支援学校"
      },
      "静岡県立浜松特別支援学校" : {
         "location_area" : "浜松市",
         "short_name" : "浜松特別支援学校"
      },
      "静岡県立浜松特別支援学校朝霧分教室" : {
         "location_area" : "浜松市",
         "short_name" : "浜松特別支援学校朝霧分教室"
      },
      "静岡県立浜松特別支援学校磐田分校" : {
         "location_area" : "浜松市",
         "short_name" : "浜松特別支援学校磐田分校"
      },
      "静岡県立浜松聴覚特別支援学校" : {
         "location_area" : "浜松市",
         "short_name" : "浜松聴覚特別支援学校"
      },
      "静岡県立浜松視覚特別支援学校" : {
         "location_area" : "浜松市",
         "short_name" : "浜松視覚特別支援学校"
      },
      "静岡県立藤枝特別支援学校" : {
         "location_area" : "藤枝市",
         "short_name" : "藤枝特別支援学校"
      },
      "静岡県立藤枝養護学校駿遠分教室" : {
         "location_area" : "藤枝市",
         "short_name" : "藤枝養護学校駿遠分教室"
      },
      "静岡県立袋井特別支援学校" : {
         "location_area" : "袋井市",
         "short_name" : "袋井特別支援学校"
      },
      "静岡県立袋井特別支援学校御前崎分校" : {
         "location_area" : "袋井市",
         "short_name" : "袋井特別支援学校御前崎分校"
      },
      "静岡県立袋井特別支援学校磐田見付分校" : {
         "location_area" : "袋井市",
         "short_name" : "袋井特別支援学校磐田見付分校"
      },
      "静岡県立袋井養護学校東遠分教室" : {
         "location_area" : "袋井市",
         "short_name" : "袋井養護学校東遠分教室"
      },
      "静岡県立西部特別支援学校" : {
         "location_area" : "浜松市",
         "short_name" : "西部特別支援学校"
      },
      "静岡県立静岡北特別支援学校" : {
         "location_area" : "静岡市",
         "short_name" : "静岡北特別支援学校"
      },
      "静岡県立静岡北特別支援学校南の丘分校" : {
         "location_area" : "静岡市",
         "short_name" : "静岡北特別支援学校南の丘分校"
      },
      "静岡県立静岡北特別支援学校安倍分教室" : {
         "location_area" : "静岡市",
         "short_name" : "静岡北特別支援学校安倍分教室"
      },
      "静岡県立静岡北特別支援学校清水分校" : {
         "location_area" : "静岡市",
         "short_name" : "静岡北特別支援学校清水分校"
      },
      "静岡県立静岡南部特別支援学校" : {
         "location_area" : "静岡市",
         "short_name" : "静岡南部特別支援学校"
      },
      "静岡県立静岡聴覚特別支援学校" : {
         "location_area" : "静岡市",
         "short_name" : "静岡聴覚特別支援学校"
      },
      "静岡県立静岡視覚特別支援学校" : {
         "location_area" : "静岡市",
         "short_name" : "静岡視覚特別支援学校"
      }
   }
}
